cz_conventional_JIRA.py
conventional_JIRA-0.1.0.dist-info/METADATA
conventional_JIRA-0.1.0.dist-info/WHEEL
conventional_JIRA-0.1.0.dist-info/top_level.txt
conventional_JIRA-0.1.0.dist-info/RECORD
